{
    "2020-01": {
        "new": 375.0,
        "used": null,
        "new_change": 0,
        "used_change": 0
    },
    "2020-02": {
        "new": 365.0,
        "used": null,
        "new_change": -10.0,
        "used_change": 0
    },
    "2020-03": {
        "new": 350.0,
        "used": null,
        "new_change": -15.0,
        "used_change": 0
    },
    "2020-04": {
        "new": 373.0,
        "used": null,
        "new_change": 23.0,
        "used_change": 0
    },
    "2020-05": {
        "new": 379.0,
        "used": null,
        "new_change": 6.0,
        "used_change": 0
    },
    "2020-06": {
        "new": 377.0,
        "used": null,
        "new_change": -2.0,
        "used_change": 0
    },
    "2020-07": {
        "new": 385.0,
        "used": null,
        "new_change": 8.0,
        "used_change": 0
    },
    "2020-08": {
        "new": 380.0,
        "used": null,
        "new_change": -5.0,
        "used_change": 0
    },
    "2020-09": {
        "new": 357.0,
        "used": null,
        "new_change": -23.0,
        "used_change": 0
    },
    "2020-10": {
        "new": 331.0,
        "used": null,
        "new_change": -26.0,
        "used_change": 0
    },
    "2020-11": {
        "new": 317.0,
        "used": null,
        "new_change": -14.0,
        "used_change": 0
    },
    "2020-12": {
        "new": 313.0,
        "used": null,
        "new_change": -4.0,
        "used_change": 0
    },
    "2021-01": {
        "new": 305.0,
        "used": null,
        "new_change": -8.0,
        "used_change": 0
    },
    "2021-02": {
        "new": 287.0,
        "used": null,
        "new_change": -18.0,
        "used_change": 0
    },
    "2021-03": {
        "new": 290.0,
        "used": null,
        "new_change": 3.0,
        "used_change": 0
    },
    "2021-04": {
        "new": 292.0,
        "used": null,
        "new_change": 2.0,
        "used_change": 0
    },
    "2021-05": {
        "new": 291.0,
        "used": null,
        "new_change": -1.0,
        "used_change": 0
    },
    "2021-06": {
        "new": 285.0,
        "used": null,
        "new_change": -6.0,
        "used_change": 0
    },
    "2021-07": {
        "new": 279.0,
        "used": null,
        "new_change": -6.0,
        "used_change": 0
    },
    "2021-08": {
        "new": 270.0,
        "used": null,
        "new_change": -9.0,
        "used_change": 0
    },
    "2021-09": {
        "new": 260.0,
        "used": null,
        "new_change": -10.0,
        "used_change": 0
    },
    "2021-10": {
        "new": 258.0,
        "used": null,
        "new_change": -2.0,
        "used_change": 0
    },
    "2021-11": {
        "new": 260.0,
        "used": null,
        "new_change": 2.0,
        "used_change": 0
    },
    "2021-12": {
        "new": 255.0,
        "used": null,
        "new_change": -5.0,
        "used_change": 0
    },
    "2022-01": {
        "new": 240.0,
        "used": null,
        "new_change": -15.0,
        "used_change": 0
    },
    "2022-02": {
        "new": 225.0,
        "used": null,
        "new_change": -15.0,
        "used_change": 0
    },
    "2022-03": {
        "new": 217.0,
        "used": null,
        "new_change": -8.0,
        "used_change": 0
    },
    "2022-04": {
        "new": 209.0,
        "used": null,
        "new_change": -8.0,
        "used_change": 0
    },
    "2022-05": {
        "new": 207.0,
        "used": 204.0,
        "new_change": -2.0,
        "used_change": 0
    },
    "2022-06": {
        "new": null,
        "used": 195.0,
        "new_change": 0,
        "used_change": -9.0
    },
    "2022-07": {
        "new": null,
        "used": 192.0,
        "new_change": 0,
        "used_change": -3.0
    },
    "2022-08": {
        "new": null,
        "used": 190.0,
        "new_change": 0,
        "used_change": -2.0
    },
    "2022-09": {
        "new": null,
        "used": 189.0,
        "new_change": 0,
        "used_change": -1.0
    },
    "2022-10": {
        "new": null,
        "used": 181.0,
        "new_change": 0,
        "used_change": -8.0
    },
    "2022-11": {
        "new": null,
        "used": 178.0,
        "new_change": 0,
        "used_change": -3.0
    },
    "2022-12": {
        "new": null,
        "used": 178.0,
        "new_change": 0,
        "used_change": 0.0
    },
    "2023-01": {
        "new": null,
        "used": 170.0,
        "new_change": 0,
        "used_change": -8.0
    },
    "2023-02": {
        "new": null,
        "used": 168.0,
        "new_change": 0,
        "used_change": -2.0
    },
    "2023-03": {
        "new": null,
        "used": 169.0,
        "new_change": 0,
        "used_change": 1.0
    },
    "2023-04": {
        "new": null,
        "used": 168.0,
        "new_change": 0,
        "used_change": -1.0
    },
    "2023-05": {
        "new": null,
        "used": 170.0,
        "new_change": 0,
        "used_change": 2.0
    },
    "2023-06": {
        "new": null,
        "used": 162.0,
        "new_change": 0,
        "used_change": -8.0
    },
    "2023-07": {
        "new": null,
        "used": 161.0,
        "new_change": 0,
        "used_change": -1.0
    },
    "2023-08": {
        "new": null,
        "used": 169.0,
        "new_change": 0,
        "used_change": 8.0
    },
    "2023-09": {
        "new": null,
        "used": 160.0,
        "new_change": 0,
        "used_change": -9.0
    },
    "2023-10": {
        "new": null,
        "used": 158.0,
        "new_change": 0,
        "used_change": -2.0
    },
    "2023-11": {
        "new": null,
        "used": 150.0,
        "new_change": 0,
        "used_change": -8.0
    },
    "2023-12": {
        "new": null,
        "used": 150.0,
        "new_change": 0,
        "used_change": 0.0
    },
    "2024-01": {
        "new": null,
        "used": 140.0,
        "new_change": 0,
        "used_change": -10.0
    },
    "2024-02": {
        "new": null,
        "used": 136.0,
        "new_change": 0,
        "used_change": -4.0
    },
    "2024-03": {
        "new": null,
        "used": 130.0,
        "new_change": 0,
        "used_change": -6.0
    },
    "2024-04": {
        "new": null,
        "used": 130.0,
        "new_change": 0,
        "used_change": 0.0
    },
    "2024-05": {
        "new": null,
        "used": 125.0,
        "new_change": 0,
        "used_change": -5.0
    },
    "2024-06": {
        "new": null,
        "used": 125.0,
        "new_change": 0,
        "used_change": 0.0
    },
    "2024-07": {
        "new": null,
        "used": 123.0,
        "new_change": 0,
        "used_change": -2.0
    },
    "2024-08": {
        "new": null,
        "used": 125.0,
        "new_change": 0,
        "used_change": 2.0
    }
}